pypipeline/__init__.py
pypipeline/action.py
pypipeline/cli.py
pypipeline/constants.py
pypipeline/filter.py
pypipeline/item.py
pypipeline/items_container.py
pypipeline/modifier.py
pypipeline/pipeline.py
pypipeline/util.py
pypeline_python-0.1.8.dist-info/LICENSE
pypeline_python-0.1.8.dist-info/METADATA
pypeline_python-0.1.8.dist-info/WHEEL
pypeline_python-0.1.8.dist-info/top_level.txt
pypeline_python-0.1.8.dist-info/RECORD
