Metadata-Version: 2.1
Name: pypeline-python
Version: 0.1.8
Summary: PyPipeline is a simple Python framework for building data processing pipelines.
Home-page: https://github.com/zigai/py-pipeline
Author: Žiga Ivanšek
Author-email: ziga.ivansek@gmail.com
License: MIT
Classifier: Programming Language :: Python
Classifier: Programming Language :: Python :: 3.10
Classifier: Programming Language :: Python :: 3.11
Classifier: Programming Language :: Python :: 3.12
Classifier: Programming Language :: Python :: 3 :: Only
Classifier: Topic :: Software Development :: Libraries :: Python Modules
License-File: LICENSE
Requires-Dist: stdl>=0.5.4
Requires-Dist: tqdm
Requires-Dist: docstring-parser>=0.15
Requires-Dist: objinspect>=0.2.13
